alibabacloud_xgippop20220520/__init__.py
alibabacloud_xgippop20220520/client.py
alibabacloud_xgippop20220520/models.py
alibabacloud_xgippop20220520_py2-1.0.65.dist-info/LICENSE
alibabacloud_xgippop20220520_py2-1.0.65.dist-info/METADATA
alibabacloud_xgippop20220520_py2-1.0.65.dist-info/WHEEL
alibabacloud_xgippop20220520_py2-1.0.65.dist-info/top_level.txt
alibabacloud_xgippop20220520_py2-1.0.65.dist-info/RECORD
